{
    "_source_references": {
        "tax_brackets": {
            "source": "nz_personal_tax_rules.json: year 1990 entry",
            "reference_ids": [
                "152018581057803-L24-L26",
                "152018581057803-L24-L27"
            ],
            "notes": "Values are taken directly from the source file."
        },
        "ietc": {
            "source": "Placeholder",
            "notes": "Policy did not exist in this year (starts 2009)."
        },
        "wff": {
            "source": "Placeholder",
            "notes": "Policy did not exist in this year (starts 2005)."
        },
        "ppl": {
            "source": "Placeholder",
            "notes": "Policy did not exist in this year (starts 2002)."
        },
        "child_support": {
            "source": "Placeholder",
            "notes": "Policy did not exist in this year (starts 1991)."
        },
        "acc_levy": {
            "source": "Placeholder",
            "notes": "NEEDS RESEARCH. The ACC levy rate and income cap for 1990 are unknown. Using 2005 values as a placeholder."
        }
    },
    "tax_brackets": {
        "rates": [
            0.24,
            0.33
        ],
        "thresholds": [
            30875
        ]
    },
    "ietc": null,
    "wff": null,
    "ppl": null,
    "child_support": null,
    "acc_levy": {
        "rate": 0.0153,
        "max_income": 139111
    }
}